tinyslurpy/__init__.py
tinyslurpy/__main__.py
tinyslurpy-0.1.3.dist-info/METADATA
tinyslurpy-0.1.3.dist-info/WHEEL
tinyslurpy-0.1.3.dist-info/RECORD
