Metadata-Version: 2.1
Name: tinyslurpy
Version: 0.1.3
Summary: Slurm job helper - please alias as slurpy :)
Author: Jeff Shen
Author-email: shenjeff@princeton.edu
Requires-Python: >=3.10,<4.0
Classifier: Programming Language :: Python :: 3
Classifier: Programming Language :: Python :: 3.10
Classifier: Programming Language :: Python :: 3.11
Classifier: Programming Language :: Python :: 3.12
